heapmap/__init__.py
heapmap-0.1.0.dist-info/licenses/LICENCE
heapmap-0.1.0.dist-info/METADATA
heapmap-0.1.0.dist-info/WHEEL
heapmap-0.1.0.dist-info/top_level.txt
heapmap-0.1.0.dist-info/RECORD
