Metadata-Version: 2.4
Name: heapmap
Version: 0.1.0
Summary: A thread-safe, map-backed min/max heap implementation for Python.
Home-page: https://github.com/amanabiy/heapmap
Author: Amanuel Sisay
License: MIT
Keywords: heap,priority queue,minheap,maxheap,data structures,dijkstra,algorithm,sorting,map,thread-safe
Classifier: Development Status :: 3 - Alpha
Classifier: Intended Audience :: Developers
Classifier: Topic :: Software Development :: Libraries
Classifier: Topic :: Utilities
Classifier: Programming Language :: Python :: 3
Classifier: Programming Language :: Python :: 3.7
Classifier: Programming Language :: Python :: 3.8
Classifier: Programming Language :: Python :: 3.9
Classifier: Programming Language :: Python :: 3.10
Classifier: License :: OSI Approved :: MIT License
Classifier: Operating System :: OS Independent
Requires-Python: >=3.7
License-File: LICENCE
Dynamic: license-file
